[
  {
    "code": "1961",
    "name": "Semi Counter Basin",
    "price": 16500,
    "finish": "White"
  },
  {
    "code": "1941",
    "name": "Three Hole Semi Counter Basin 1962 1963 AB Three Hole Semi Counter White Basin SS Stand Basin\u0003Size\u0003 Stand\u0003Size\u0003 Set\u0003Size\u0003 1962 1963 G Three Hole Semi Counter White Basin SS Stand Basin\u0003Size\u0003 Stand\u0003Size\u0003 Set\u0003Size\u0003",
    "price": 77000,
    "finish": "Gold"
  },
  {
    "code": "1962",
    "name": "Three Hole Semi Counter Basin",
    "price": 17500,
    "finish": "White"
  },
  {
    "code": "1942",
    "name": "Semi Counter Basin 1963 AB Antique Bronze 1963 G Gold",
    "price": 59500,
    "finish": "White"
  },
  {
    "code": "1953",
    "name": "Table Mounted Basin 08 CLASSICAL TOILETS Wooden Seat Cover Walnut Colour 1871 AB W 1 Piece Floor Mounted Couple Suite S Trap Seat Cover White 1857 W Generation 3 Rimless Tornado Sil",
    "price": 44500,
    "finish": "Antique Bronze"
  },
  {
    "code": "1321",
    "name": "Three-Hole Brass Table Mounted Basin Gold Handles",
    "price": 63500,
    "finish": "Glossy Gold"
  },
  {
    "code": "1325",
    "name": "Three-Hole Brass Table Mounted Basin Grey Handles",
    "price": 63500,
    "finish": "Graphite Grey"
  },
  {
    "code": "1322",
    "name": "Three-Hole Brass Wall Mounted Basin Amber Gold Handles",
    "price": 63500,
    "finish": "Glossy Gold"
  },
  {
    "code": "1326",
    "name": "Three-Hole Brass Wall Mounted Basin Glacier Grey Handles 2652 GG Visible Waterfall Flow Graphite Grey 2653 GG",
    "price": 49500,
    "finish": "Graphite Grey"
  },
  {
    "code": "1323",
    "name": "Three-Hole Brass Table Mounted Ruby Red Handles",
    "price": 63500,
    "finish": "Matt Black"
  },
  {
    "code": "1327",
    "name": "Three-Hole Brass Table Mounted Basin Mixer in Brushed Rose Gold Finish Brushed Rose Gold 2652 BRG Visible Waterfall Flow Brushed Rose Gold 2653 BRG Brass & Glass Wall Mounted Basin Mixer Brushed Rose Gold",
    "price": 67500
  },
  {
    "code": "1324",
    "name": "Three-Hole Brass Walll Mounted Ruby Red Handles",
    "price": 63500,
    "finish": "Matt Black"
  },
  {
    "code": "1328",
    "name": "Three-Hole Brass Wall Mounted Basin Mixer in Brushed Rose Gold Finish Brushed Rose Gold",
    "price": 47500
  },
  {
    "code": "1329",
    "name": "Three-Hole Brass Wall Mounted Basin Statuario Marble Handles The Transparent Glass reveals the flowing water turning motion into visual art A modern statement piece where classical material meets modern design that turns everyday use into a captivating experience 2652 BG Visible Waterfall Flow Brushed Gold 2653 BG Brass & Glass Wall Mounted Basin Mixer Brushed Gold FAUCETS & SHOWERING SYSTEMS IN SPECIAL FINISHES Marbella Series 14 1334 BG 1333 Complete Set Including \u0003Brass\u0003Rain\u0003Shower\u0003\u0003l\u0003\u0003Size\u0003 \u0003Brass\u0003Shower\u0003Arm\u0003\u0003l\u0003\u0003Size\u0003 Brass Plain Spout Brushed Gold 1334 BRG 1333 Complete Set Including \u0003Brass\u0003Rain\u0003Shower\u0003\u0003l\u0003\u0003Size\u0003 \u0003Brass\u0003Shower\u0003Arm\u0003\u0003l\u0003\u0003Size\u0003 Brass Plain Spout Brushed Rose Gold 1334 GG 1333 Complete Set Including \u0003Brass\u0003Rain\u0003Shower\u0003\u0003l\u0003\u0003Size\u0003 \u0003Brass\u0003Shower\u0003Arm\u0003\u0003l\u0003\u0003Size\u0003 Brass Plain Spout Graphite Grey CUSTOMISABLE STONE HANDLES Upgrad",
    "price": 1,
    "finish": "Brushed Gold"
  },
  {
    "code": "2612",
    "name": "Tall Brass Basin Mixer Graphite Grey Rose Gold",
    "price": 29950
  },
  {
    "code": "2048",
    "name": "Tall Brass Basin Mixer Black Rose Gold",
    "price": 29950
  },
  {
    "code": "2611",
    "name": "Brass Basin Mixer Graphite Grey Rose Gold",
    "price": 20500
  },
  {
    "code": "2049",
    "name": "Brass Wall Mounted Basin Mixer Black Rose Gold",
    "price": 35750
  },
  {
    "code": "2047",
    "name": "Brass Basin Mixer Black Rose Gold",
    "price": 20500
  },
  {
    "code": "2613",
    "name": "Brass Wall Mounted Basin Mixer Graphite Grey Rose Gold",
    "price": 35750
  },
  {
    "code": "2050",
    "name": "Complete Set Including \u0003Brass\u0003Rain\u0003Shower\u0003\u0003l\u0003\u0003Size\u0003 \u0003Brass\u0003Shower\u0003Arm\u0003\u0003l\u0003\u0003Size\u0003 Brass Plain Spout Black Rose Gold FAUCETS & SHOWERING SYSTEMS IN SPECIAL FINISHES 2523 RGW Brass Wall Mounted Basin Mixer Matt White Rose Gold 2525 RGW Matt White Rose Gold 2535 RGB Matt Black Rose Gold 2522 RGW Tall Brass Basin Mixer Matt White Rose Gold 2532 RGB Tall Brass Basin Mixer Matt Black Rose Gold 2531 RGB Brass Basin Mixer Matt Black Rose Gold 2533 RGB Brass Wall Mounted Basin Mixer Matt Black Rose Gold 2521 RGW Brass Basin Mixer Matt White Rose Gold Curve Series - Matt Black Rose Gold 2534 RGB Complete Set Including \u0003Brass\u0003Rain\u0003Shower\u0003\u0003l\u0003\u0003Size\u0003 \u0003Brass\u0003Shower\u0003Arm\u0003\u0003l\u0003\u0003Size\u0003 Brass Plain Spout Matt Black Rose Gold Curve Series - Matt White Rose Gold 2524 RGW Complete Set Including \u0003Brass\u0003Rain\u0003Shower\u0003\u0003l\u0003\u0003Size\u0003 \u0003Brass\u0003Shower\u0003Arm\u0003\u0003l\u0003\u0003Size\u0003 Brass Plain Spout Matt White Rose Gold 18 Svelte Series - Brushed Rose Gold 2584 BRG Complete Set Including \u0003Brass\u0003Rain\u0003Shower\u0003\u0003l\u0003\u0003Size\u0003 \u0003Brass\u0003Shower\u0003Arm\u0003\u0003l\u0003\u0003Size\u0003 Progressive Cartridge D",
    "price": 73500
  },
  {
    "code": "2504",
    "name": "Complete Set Including \u0003Brass\u0003Rain\u0003Shower\u0003\u0003l\u0003\u0003Size\u0003 \u0003Brass\u0003Shower\u0003Arm\u0003\u0003l\u0003\u0003Size\u0003 Brass Plain Spout Chrome Rose Gold 2583 BRG Progressive Cartridge Brushed Rose Gold 2581 BRG Cartridge Brushed Rose Gold",
    "price": 29850
  },
  {
    "code": "2501",
    "name": "Brass Basin Mixer Chrome Rose Gold",
    "price": 16250
  },
  {
    "code": "2503",
    "name": "Brass Wall Mounted Basin Mixer Chrome Rose Gold 2582 BRG Cartridge Brushed Rose Gold",
    "price": 39750
  },
  {
    "code": "2502",
    "name": "Tall Brass Basin Mixer Chrome Rose Gold",
    "price": 23750
  },
  {
    "code": "2505",
    "name": "Chrome Rose Gold FAUCETS & SHOWERING SYSTEMS IN SPECIAL FINISHES 19 FAUCETS & SHOWERING SYSTEMS IN SPECIAL FINISHES Stellar Series- Gold 2044 G - Gold Complete Set Including \u0003Brass\u0003Rain\u0003Shower\u0003\u0003l\u0003\u0003Size\u0003 \u0003Brass\u0003Shower\u0003Arm\u0003\u0003l\u0003\u0003Size\u0003 Brass Button Spout 28121 G - Gold Flexible Hose & Wall Hook Gold 1017 G - Gold Brass Waste Coupling Gold 2041 G - Gold Brass Basin Mixer Gold 2043 G - Gold Brass Wall Mounted Basin Mixer Gold 3154 G - Gold Gold 1003 G - Gold Brass Bottle Trap Long Pipe 450-1003 G - Gold Bottle Trap Pipe 4006 G - Gold Brass Rain Shower Gold 3156 G - Gold Brass Concealed Stop-Cock Gold 1476 G - Gold Shower Arm Gold 30006 30007 G - Gold Extendible Shower Hose (SS) Gold 20 3152 G - Gold Tall Brass Pillar Cock G",
    "price": 11000,
    "finish": "l"
  },
  {
    "code": "1424-200",
    "name": "Product",
    "price": 2500
  },
  {
    "code": "1424",
    "name": "500\u0003BRG 1424-500 GG 1424-500 RG 1424-500 BG 1424-500 MB Brass Floor Mounted Spout 1317 CP 1317 BRG - Brushed Rose Gold 1317 BG - Brushed Gold 1317 GG - Graphite Grey 1317 MB - Matt Black 1317 RG - Rose Gold 40 FAUCETS IN SPECIAL FINISHES Deck Mounted Mouth Operated Tall Basin Tap 1312 CP 1312 BRG - Brushed Rose Gold 1312 BG - Brushed Gold 1312 GG - Graphite Grey 1312 MB - Matt Black 1312 RG - Rose Gold Brass Wall Mounted Mouth Operated Basin Tap 1311 CP 1311 BRG - Brushed Rose Gold 1311 BG - Brushed Gold 1311 GG - Graphite Grey 1311 MB - Matt Black 1311 RG - Rose Gold 1316 CP 1316 BRG - Brushed Rose Gold 1316 BG - Brushed Gold 1316 GG - Graphite Grey 1316 MB - Matt Black 1316 RG - Rose Gold Joystick Wall Mounted Deusch Mixer 1421 CP 1421 BRG - Brushed Rose Gold 1421 BG - Brushed Gold 1421 GG - Graphite Grey 1421 MB - Matt Black 1421 RG - Rose Gold Joystick Deck Mounted Deusch Mixer 1422 CP 1422 BRG - Brushed Rose Gold 1422 BG - Brushed Gold 1422 GG - Graphite Grey 1422 MB - Matt Black 1422 RG - Rose Gold 41 BATH FITTINGS IN SPECIAL FINISHES Square Wall Outlet (Brass Square Body) 1446 CP 1446 BRG - Brushed Rose Gold 1446 BG - Brushed Gold 1446 GG - Graphite Grey 1446 MB - Matt Black 1446 RG - Rose Gold Brass Slide Shower Rail 1441 CP 1441 BRG - Brushed Rose Gold 1441 BG - Brushed Gold 1441 GG - Graphite Grey 1441 MB - Matt Black 1441 RG - Rose Gold Brass Wall Hook Swivel 1125 CP 1125 BRG - Brushed Rose Gold 1125 BG - Brushed Gold 1125 GG - Graphite Grey 1125 MB - Matt Black 1125 RG - Rose Gold 1497 CP 1497 BRG - Brushed Rose Gold 1497 BG - Brushed Gold 1497 GG - Graphite Grey 1497 MB - Matt Black 1497 RG - Rose Gold 1442 CP 1442 BRG - Brushe",
    "price": 2400
  },
  {
    "code": "450",
    "name": "1003\u0003CP 1186 CP 1186 BRG - Brushed Rose Gold 1186 BG - Brushed Gold 1186 GG - Graphite Grey 1186 MB - Matt Black 1186 RG - Rose Gold ALLIED PRODUCTS IN SPECIAL FINISHES 1003 BRG - Brushed Rose Gold 1003 BG - Brushed Gold 1003 GG - Graphite Grey 1003 MB - Matt Black 1003 RG - Rose Gold 450-1003 BRG 450-1003 GG 450-1003 RG 450-1003 BG 450-1003 MB 43 ACCESSORIES IN SPECIAL FINISHES 44 Stainless Steel Niche For Toilet Paper Roll and Toilet Brush 7011 BRG - Brushed Rose Gold 7011 BG - Brushed Gold 7011 GG - Graphite Grey 7011 MB - Matt Black 2650 BRG - Brushed Rose Gold 2650 BG - Brushed Gold 2650 GG - Graphite Grey 2650 MB - Matt Black 2650 SS - Stainless Steel 7012 SS - Stainless Steel Tile Insert Niche For Toilet Paper Roll & Toilet Brush ACCESSORIES IN SPECIAL FINISHES",
    "price": 35000
  },
  {
    "code": "2571",
    "name": "Brass Basin Mixer Slender Series",
    "price": 13500
  },
  {
    "code": "2574",
    "name": "Single Lever Diverter Three Outlets Brass Concealed Body 15mm inlet Seina Series",
    "price": 16950
  },
  {
    "code": "2573",
    "name": "Brass Wall Mounted Basin Mixer",
    "price": 23950
  },
  {
    "code": "2085",
    "name": "Brass Basin Mixer",
    "price": 11500
  },
  {
    "code": "2511",
    "name": "Brass Basin Mixer",
    "price": 18500
  },
  {
    "code": "2514",
    "name": "Crystal Series",
    "price": 22500
  },
  {
    "code": "2087",
    "name": "Brass Wall Mounted Basin Mixer",
    "price": 25250
  },
  {
    "code": "2086",
    "name": "Tall Brass Basin Mixer",
    "price": 17250
  },
  {
    "code": "2513",
    "name": "Brass Wall Mounted Basin Mixer",
    "price": 26250
  },
  {
    "code": "2512",
    "name": "Tall Brass Basin Mixer",
    "price": 26250
  },
  {
    "code": "2090",
    "name": "Brass Button Spout",
    "price": 10500
  },
  {
    "code": "2089",
    "name": "Brass Plain Spout",
    "price": 6900
  },
  {
    "code": "2515",
    "name": "Product",
    "price": 3750
  },
  {
    "code": "2516",
    "name": "Brass Plain Spout",
    "price": 6950
  },
  {
    "code": "2572",
    "name": "Tall Brass Basin Mixer 50 FAUCETS & SHOWERING SYSTEMS IN CHROME FINISH Cube Series",
    "price": 19500
  },
  {
    "code": "3115",
    "name": "Brass 2 Way Bib Cock",
    "price": 4250
  },
  {
    "code": "3112",
    "name": "Brass Tall Body Pillar Cock",
    "price": 7250
  },
  {
    "code": "3113",
    "name": "Brass Bib Cock",
    "price": 7350
  },
  {
    "code": "3114",
    "name": "Product",
    "price": 1650
  },
  {
    "code": "3111",
    "name": "Brass Pillar Cock",
    "price": 5200
  },
  {
    "code": "2022",
    "name": "Brass Basin Mixer",
    "price": 11000
  },
  {
    "code": "2023",
    "name": "Tall Brass Basin Mixer",
    "price": 17500
  },
  {
    "code": "2024",
    "name": "Brass Wall Mounted Basin Mixer",
    "price": 18500
  },
  {
    "code": "2013",
    "name": "Brass Concealed Body",
    "price": 20500
  },
  {
    "code": "2026",
    "name": "Brass Concealed Body",
    "price": 15500
  },
  {
    "code": "2025",
    "name": "Brass Concealed Body 51 SHOWERING SYSTEMS IN CHROME FINISH Concealed Ceiling Mounted LED Multi-Function Shower 5013 CP - HydroAuro Flows Rain Rain-Column Mist Dual Waterfall (Requires electric point) CHROMOTHERAPY Concealed Ceiling Mounted Multi-Function Showers 5123 CP - HydroTorrent Flows Rain Dual Powder Flow Mist 5122 CP - HydroVortex Flows Jewel Powder Flow Dancing Wave 52 Brass Rain Shower",
    "price": 99500
  },
  {
    "code": "4001",
    "name": "Product",
    "price": 3300
  },
  {
    "code": "4003",
    "name": "Product",
    "price": 5200
  },
  {
    "code": "4005",
    "name": "Product",
    "price": 8350
  },
  {
    "code": "4007",
    "name": "Brass Rain S",
    "price": 11500
  },
  {
    "code": "4000",
    "name": "Product",
    "price": 3100
  },
  {
    "code": "4002",
    "name": "Product",
    "price": 4100
  },
  {
    "code": "4004",
    "name": "Brass Rain Shower",
    "price": 5750
  },
  {
    "code": "4008",
    "name": "Product",
    "price": 13250
  },
  {
    "code": "4010",
    "name": "Product",
    "price": 26250
  },
  {
    "code": "1485",
    "name": "ABS Waterfall Shower Bath Spout 0 ABS Waterfall Shower CONCEALED CEILING MOUNTED SHOWERS IN CHROME FINISH 5111 - HydroRain SS 1 Function Concealed Ceiling Mounted Ceiling Flows Rain 5104 CP - HydroRain SS 1 Function Concealed Ceiling Mounted Ceiling Flows Rain 5101 - HydroRain SS 1 Function Concealed Ceiling Mounted Ceiling Flows Rain 5120 - HydroRain SS 1 Function Concealed Ceiling Mounted Ceiling Flows Rain 5112 - HydroMist SS 2 Function Concealed Ceiling Mounted Ceiling Flows Rain Mist 5105 CP - HydroMist SS 2 Function Concealed Ceiling Mounted Ceiling Flows Rain Mist 5102 - HydroMist SS 2 Function Concealed Ceiling Mounted Ceiling Flows Rain Mist 5121 - HydroMist SS 2 Function Concealed Ceiling Mounted Ceiling Flows Rain Mist 5114 - HydroBliss SS 3 Function Concealed Ceiling Mounted Ceiling Flows Rain Mist Waterfall 5109 - HydroBliss SS 3 Function Concealed Ceiling Mounted Ceiling Flows Rain Waterfall Mist 5108 - HydroBliss SS 3 Function Concealed Ceiling Mounted Ceiling Flows Rain Waterfall Mist 5107 CP - HydroBliss SS 3 Function Concealed Ceiling Mounted Ceiling Flows Rain Dual Waterfall Mist 5113 -",
    "price": 82500
  },
  {
    "code": "28157",
    "name": "ABS Head Shower",
    "price": 1375
  },
  {
    "code": "28158",
    "name": "ABS Hand Shower",
    "price": 1375
  },
  {
    "code": "28041",
    "name": "ABS Head Shower",
    "price": 2250
  },
  {
    "code": "28040",
    "name": "ABS Hand Shower Flows Normal Massage Jet Mist Foam",
    "price": 2250
  },
  {
    "code": "28190",
    "name": "Flexible Hose Flows Shower Mist Waterfall Shower 28187 CP 1 5 mtr Flexible Hose",
    "price": 4500
  },
  {
    "code": "28189",
    "name": "ABS Head Shower",
    "price": 1150
  },
  {
    "code": "28188",
    "name": "ABS Hand Shower",
    "price": 1150
  },
  {
    "code": "28156",
    "name": "ABS Head Shower",
    "price": 1850
  },
  {
    "code": "28155",
    "name": "ABS Hand Shower Flows Normal Massage Jet Mist 28191 CP Flexible Hose Flows Shower Mist Dual-Mist & Shower",
    "price": 4500
  },
  {
    "code": "28198",
    "name": "ABS Hand Shower",
    "price": 700
  },
  {
    "code": "28197",
    "name": "ABS Head Shower",
    "price": 700
  },
  {
    "code": "28196",
    "name": "ABS Head Shower ABS Single Function Showers 28194 CP 1 5 mtr Flexible Hose",
    "price": 5500
  },
  {
    "code": "1155",
    "name": "ABS Head Shower",
    "price": 950
  },
  {
    "code": "28202",
    "name": "ABS Head Shower",
    "price": 3000
  },
  {
    "code": "28201",
    "name": "ABS Hand Shower Set Flows Shower Mist Columnar Foam Spray Massage Bubble & Sprinkle 54 ALLIED PRODUCTS IN CHROME FINISH 1476 CP Brass Shower Arm",
    "price": 3650
  },
  {
    "code": "1488",
    "name": "Brass Shower Arm",
    "price": 5
  },
  {
    "code": "28011",
    "name": "Product",
    "price": 1350
  },
  {
    "code": "1130",
    "name": "Brass Shower Arm",
    "price": 3675
  },
  {
    "code": "1458",
    "name": "Brass Vertical Shower Arm",
    "price": 1600
  },
  {
    "code": "1198",
    "name": "Product",
    "price": 2950
  },
  {
    "code": "1127",
    "name": "Brass Shower Arm 1457 CP Brass Vertical Shower Arm Shower Rails 1441 CP Brass Slide Shower Rail Shower Arms",
    "price": 8500
  },
  {
    "code": "1128",
    "name": "Brass Shower Arm",
    "price": 2400
  },
  {
    "code": "1129",
    "name": "Brass Shower Arm 1456 CP Brass Shower Arm 55 1208 - Allure Stainless Steel Shower Panel Matt Finish 1258 - Revive Thermostatic Diverter Matt Finish Single-Lever Shower Panels 1257 - Retro Stainless Steel Shower Panel Matt Finish Thermostatic Shower Panels 1256 - Eden Thermostatic Diverter Matt Finish SS SHOWER PANELS IN MATT FINISH 1245 - Divine Stainless Steel Shower Panel Matt Finish 56 Outdoor Shower Panel 1259 - Lagoon (316SS)\u0003Stainless\u0003Steel\u0003Out\u0003Door\u0003Shower\u0003Panel\u0003With\u0003Progressive\u0003Diverter\u0003Includes\u0003 Matt Finish Brass Shower Column 1438 - Flora •\u0003ABS\u0003Rain\u0003Shower\u0003\u0003l\u0003\u0003Size\u0003 Hidden Spout Graphite Grey 1439 - Fleur Brass Shower Column •\u0003ABS\u0003Rain\u0003Shower\u0003\u0003l\u0003\u0003Size\u0003 Single Lever Piano Button Diverter Hidden Spout Chrome 57 SHOWER PANELS IN SPECIAL & CHROME FINISH Pop-Up Brass Stainless Steel Drains Invisible Tile Insert Drainers",
    "price": 57500
  },
  {
    "code": "1481",
    "name": "Pop-Up Floor Trap (Grade 204 SS) Tile Insert Drains",
    "price": 615
  },
  {
    "code": "1430",
    "name": "Cockroach Shower Channel Base (304 SS) 60080 BS 750080 BS 90080 BS 120080 BS",
    "price": 6100
  },
  {
    "code": "1431",
    "name": "Cockroach Shower Channel Base (304 SS) 60080 BS CH 120080 BS CH FLOOR DRAINS IN STAINLESS STEEL Brass Drain",
    "price": 11000
  },
  {
    "code": "1432",
    "name": "Invisible Tile Insert Shower Channel Drainer Channel Drainers Line-Design Shower Channel Drain Without Base (304 SS) 60080 TL 750080 TL 90080 TL 120080 TL",
    "price": 6700
  },
  {
    "code": "1429",
    "name": "Pop-Up Floor Trap (Grade 304 SS) Matt Finish",
    "price": 1550
  },
  {
    "code": "1433",
    "name": "Invisible Tile Insert Drainer (304 SS) Tile-Insert Shower Channel Drain Without Base (304 SS) 60080 TI 750080 TI 90080 TI 120080 TI 58 Tile Insert 1318 BRG - Brushed Rose Gold 1318 BG - Brushed Gold 1318 GG - Graphite Grey 1318 MB - Matt Black 1320-750 BRG - Brushed Rose Gold 1320-750 BG - Brushed Gold 1320-750 GG - Graphite Grey 1320-750 MB - Matt Black Tile Insert 1319 BRG - Brushed Rose Gold 1319 BG - Brushed Gold 1319 GG - Graphite Grey 1319 MB - Matt Black Channel Drainers 1437-750 BRG - Brushed Rose Gold 1437-750 BG - Brushed Gold 1437-750 GG - Graphite Grey 1437-750 MB - Matt Black Shower Drainer (304 SS) 1436 BRG - Brushed Rose Gold 1436 BG - Brushed Gold 1436 GG - Graphite Grey 1436 MB - Matt Black FLOOR DRAINS IN SPECIAL FINISHES 59 KITCHEN FAUCETS IN SPECIAL & CHROME FINISH",
    "price": 4750
  },
  {
    "code": "2039",
    "name": "Brass Table Mounted Sink Mixer",
    "price": 11250
  },
  {
    "code": "2040",
    "name": "Brass Pull-Out Table-Mounted Sink Mixer Kitchen Faucets in Matt SS Finish Kitchen Faucets in Special Finishes",
    "price": 19500
  },
  {
    "code": "3126",
    "name": "Brass Wall Mounted Sink Cock",
    "price": 6
  },
  {
    "code": "2021",
    "name": "Brass 3-Inlet Kitchen Sink Mixer Table-Mounted Installation 2567 CP Brass Pull-Out Table-Mounted Sink Mixer Flows Spray & Foam Kitchen Faucets in Chrome Finish",
    "price": 21000
  },
  {
    "code": "2038",
    "name": "Brass Flexible Table-Mounted Sink Mixer Flows Spray & Foam 2091 - Stainless Steel Stainless Steel Table Mounted Matt Finish Adjustable Sink Mixer",
    "price": 15000
  },
  {
    "code": "1308",
    "name": "Brass Wall Mounted Sink Cock 2640 AB - Antique Bronze Brass Pull-Out Table-Mounted Sink Mixer Flows Spray & Foam 2567 BRG Brushed Rose Gold Brass Pull-Out Table-Mounted Sink Mixer Flows Spray & Foam 2005 - Stainless Steel Stainless Steel Wall Mounted Matt-Finish Adjustable Sink Cock",
    "price": 8500
  },
  {
    "code": "3129",
    "name": "Brass Flexible Wall Mounted Sink Cock 2567 BG - Brushed Gold Brass Pull-Out Table-Mounted Sink Mixer Flows Spray & Foam 2640 CP Brass Pull-Out Table-Mounted Sink Mixer Flows Spray & Foam 2006 - Stainless Steel Stainless Steel Wall Mounted Matt-Finish Adjustable Sink Mixer",
    "price": 15500
  },
  {
    "code": "3128",
    "name": "Brass Flexible Table Mounted Sink Cock 2567 GG - Graphite Grey Brass Pull-Out Table-Mounted Sink Mixer Flows Spray & Foam 2640 G - Gold Brass Pull-Out Table-Mounted Sink Mixer Flows Spray & Foam 60",
    "price": 38500
  },
  {
    "code": "3127",
    "name": "Brass Table Mounted Sink Cock",
    "price": 7300
  },
  {
    "code": "3131",
    "name": "SS 304 Kitchen Sink Mixer",
    "price": 9500
  },
  {
    "code": "2030",
    "name": "Brass Table-Mounted Sink Cock for RO Connection BATH COMPONENTS",
    "price": 5800
  },
  {
    "code": "1498",
    "name": "Brass Mirror (Dual) (3x & 1x Magnification)",
    "price": 4500
  },
  {
    "code": "1551",
    "name": "Wooden Bath Chair (Teak Wood) Weight Capacity 150kg",
    "price": 24000
  },
  {
    "code": "1471",
    "name": "Brass Mirror (3x Magnification) 1186 CP Flexible Hose & Wall Hook",
    "price": 1550
  },
  {
    "code": "28053",
    "name": "Flexible Hose & Wall Hook",
    "price": 1450
  },
  {
    "code": "1550",
    "name": "Wooden Bath Chair (Teak Wood) Weight Capacity 90kg 1472 CP (3x Magnification) (Requires electric point) White & Yellow Light",
    "price": 21250
  },
  {
    "code": "28088",
    "name": "ABS Wall Hook 1552 B UF Bath Chair Black Weight Capacity 150",
    "price": 120
  },
  {
    "code": "1504",
    "name": "White PVC Bath Chair (Metal Base) Weight Capacity 90kg Mirrors",
    "price": 4950
  },
  {
    "code": "1480",
    "name": "(3x Magnification) (Requires electric point) White & Yellow Light Health Faucets 28121 CP Flexible Hose & Wall Hook Wall Hooks 1125 CP Brass Wall Hook Swivel 1552 W UF Bath Chair White Weight Capacity 150 kg 61 BATH COMPONENTS",
    "price": 15950
  },
  {
    "code": "1167",
    "name": "Brass Button Spout",
    "price": 3850
  },
  {
    "code": "2090",
    "name": "Brass Button Spout",
    "price": 10500
  },
  {
    "code": "1157",
    "name": "Brass Plain Spout",
    "price": 2100
  },
  {
    "code": "2516",
    "name": "Brass Plain Spout",
    "price": 6950
  },
  {
    "code": "1158",
    "name": "Brass Button Spout",
    "price": 2400
  },
  {
    "code": "1407",
    "name": "Brass Button Spout",
    "price": 4650
  },
  {
    "code": "1138",
    "name": "Brass Plain Spout",
    "price": 2200
  },
  {
    "code": "1452",
    "name": "Brass Plain Spout 1415 CP Brass Button Spout 2565 CP Brass Button Spout",
    "price": 4800
  },
  {
    "code": "2089",
    "name": "Brass Plain Spout 2566 CP Brass Plain Spout 62",
    "price": 3550
  },
  {
    "code": "1402",
    "name": "Brass Button Spout 1419 CP Brass Button Spout 1418 CP Brass Plain Spout",
    "price": 5500
  },
  {
    "code": "1406",
    "name": "Brass Plain Spout Spouts 1411 CP Brass Plain Spout",
    "price": 3550
  },
  {
    "code": "1412",
    "name": "Brass Button Spout 2645 CP Brass Button Spout 2646 CP Brass Plain Spout BATH COMPONENTS Wall Outlets 1442 CP (Brass Round Body)",
    "price": 2400
  },
  {
    "code": "1306",
    "name": "Hook (Brass Round Body)",
    "price": 3450
  },
  {
    "code": "1305",
    "name": "Hook (Brass Square Body) Waste Coupling Pop-Up Waste Coupling 1001 - FT 1001 - HT 1017 - CP 1018 - FT",
    "price": 2150
  },
  {
    "code": "1447",
    "name": "Round Wall Outlet (Brass Round Body) Brass Bottle Traps 1003 CP Bottle Trap (Brass Body) 450-1003 CP WC Connectors",
    "price": 2100
  },
  {
    "code": "1460",
    "name": "WC Connector",
    "price": 500
  },
  {
    "code": "1462",
    "name": "WC Connector",
    "price": 550
  },
  {
    "code": "1487",
    "name": "WC Offset Connector Extendible Shower Hose (SS) - Size\u0003 30006 CP 30007\u0003CP\u0003 \u0003- Size\u0003 Shower Hose",
    "price": 690
  },
  {
    "code": "1024",
    "name": "PVC Space Saver Bottle Trap 1497 CP (Brass Square Body)",
    "price": 2400
  },
  {
    "code": "1461",
    "name": "WC Rubber Washer",
    "price": 80
  },
  {
    "code": "1010",
    "name": "Liquid Cleaner for Chrome & Colour Fitting Faucet Reviver Zinc Bottle Trap",
    "price": 950
  },
  {
    "code": "1012",
    "name": "Bottle Trap (Zinc Body Brass Nut) Brass Angle Valve 1491 CP Connectors Wire - Knitted Hose (Heavy Grade 304 SS)",
    "price": 1175
  },
  {
    "code": "1151",
    "name": "Product",
    "price": 220
  },
  {
    "code": "1152",
    "name": "Product",
    "price": 240
  },
  {
    "code": "1153",
    "name": "1446 CP Square Wall Outlet (Brass Square Body) Overflow Set",
    "price": 1900
  },
  {
    "code": "1006",
    "name": "PVC Pop-up Bath Tub Overflow Set",
    "price": 1800
  },
  {
    "code": "1341",
    "name": "(Brass Square Body) 63 STONE WASH BASINS 64 Carrara Marble Basin Carrara Marble 9273 - Apollo Carrara Carrara Marble Pedestal Wash Basin Carrara Marble 9242 - Stella Carrara Carrara Marble Basin Carrara Marble Italian Carrara Marble Collection 9244 - Bella Carrara Carrara Marble Basin Carrara Marble 9272 - Astraea Carrara Carrara Marble Pedestal Wash Basin Carrara Marble 9241 - Circa Carrara Carrara Marble Basin Carrara Marble 9274 - Infinity Carrara Carrara Marble Pedestal Wash Basin Carrara Marble 9243 - Vector Carrara Carrara Marble Basin Carrara Marble Italian Carrara stone basins are crafted from world-renowned Carrara marble from Tuscany Italy known for its soft white base and delicate grey veining Each basin is variations in pattern and tone Smooth durable and elegant these basins add refined luxury to bathrooms seamlessly complementing both modern and classic interiors A true statement of craftsmanship and timeless style STONE WASH BASINS 65 9229 - Vector Portoro Portoro Gold Marble Basin Portoro Gold Marble Turkey Green Marble Stone C",
    "price": 49500
  },
  {
    "code": "1023",
    "name": "Stone Pop-Up Waste Coupling Stone Pop-Up Waste Coupling 9205 - Vector Gold Honey Onyx Stone Basin Honey Onyx Portoro Gold stone basins feature a veining creating a bold luxurious statement that reflects timeless opulence and refined taste Honey Onyx basins are admired for their warm golden tones and natural radiant glow when illuminated each basin is a unique blend of functionality art and exclusivity pairing beautifully Rosso Levanto stone basins feature veining The rich color adds warmth and depth to any space Each basin uniquely patterned Alpi Verdi stone basins are distinguished by their deep green tones and flowing white veins The stone reflects the beauty of natural alpine landscapes Its rich color adds a sense of luxury and tranquility Alpi Verdi neutral tones A perfect balance of elegance and nature-inspired design STONE WASH BASINS Indonesian Cream Stone Marble Pedestal Basin Collection 9060 - Caves Crema Stone Pedestal Wash Basin Indonesian Marble 9051 - Nirvana Stone Pedestal Wash Basin Indonesian Marble 9063 - Zeus Indonesian Marble 9054 - Asura Stone Pedestal Wash Basin Indonesian Marble 9065 - Caves C",
    "price": 74500
  },
  {
    "code": "8103",
    "name": "LED Light (Needs Electric Point) Clear Glass 8104 AO - Amber Orange Crystal Basin Amber Orange 8104 MT - Mystical Turquoise Crystal Basin Mystical Turquoise Crystalline Series Glassy Series",
    "price": 99000
  },
  {
    "code": "8101",
    "name": "Semi Counter Table Mounted Glass Basin Brownish Black 8104 CI - Crystal Ice Crystal Basin Crystal Ice 8104 IR - Inferno Red Crystal Basin Inferno Red",
    "price": 99000
  },
  {
    "code": "8102",
    "name": "Table Mounted Glass Basin Olive Greenish 8104 GB - Glacier Blue Crystal Basin Glacier Blue 8104 GS - Graphite Smoke Crystal Basin Graphite Smoke 73 ARTISTIC WASH BASINS IN UNIQUE MATERIALS CERAMIC SANITARY WARE IN SPECIAL FINISHES 74 1922 SG - Seafoam Green Table Mounted Seafoam Green 1922 RN - Royal Navy Table Mounted Royal Navy 1921 SG - Seafoam Green Table Mounted Seafoam Green 1643 SG - Seafoam Green Urinal Back Inlet Back-Floor Outlet Seafoam Green 1643 RN - Royal Navy Urinal Back Inlet Back-Floor Outlet Royal Navy 1921 RN - Royal Navy Table Mounted Royal N",
    "price": 21000
  },
  {
    "code": "7077",
    "name": "Table Mounted Brown Marble Finish 7081 B - Glossy Black Table Mounted Black",
    "price": 13500
  },
  {
    "code": "7084",
    "name": "Table Mounted White 7082 MB - Matt Black Table Mounted Black 7081 BC - Beige Caramel Table Mounted Beige Caramel",
    "price": 13500
  },
  {
    "code": "7083",
    "name": "Table Mounted Black 7076 RGB - Rose Gold Matt Black Table Mounted Ros",
    "price": 13500
  },
  {
    "code": "1742",
    "name": "White Pot Basins 1794 W - White Table Mounted Pot Basin White",
    "price": 25000
  },
  {
    "code": "1781",
    "name": "White 1794 MB - Matt Black Table Mounted Pot Basin Matt Black",
    "price": 35000
  },
  {
    "code": "1949",
    "name": "White 1794 SM - Statuario Marble Table Mounted Pot Basin Statuario Marble",
    "price": 29500
  },
  {
    "code": "1950",
    "name": "Wall Table Mounted Without Tap Hole White 1794 BM - Marquina Marble Table Mounted Pot Basin Marquina Marble CERAMIC WASH BASINS 82 Wash Basins",
    "price": 29500
  },
  {
    "code": "1537",
    "name": "Table Wall Mounted",
    "price": 4500,
    "finish": "White"
  },
  {
    "code": "1718",
    "name": "Table Mounted",
    "price": 6450,
    "finish": "White"
  },
  {
    "code": "1727",
    "name": "Table Mounted",
    "price": 14250,
    "finish": "White"
  },
  {
    "code": "1740",
    "name": "Table Mounted",
    "price": 9900,
    "finish": "White"
  },
  {
    "code": "1758",
    "name": "Table Wall Mounted",
    "price": 8950,
    "finish": "White"
  },
  {
    "code": "1714",
    "name": "Table Mounted",
    "price": 6500,
    "finish": "White"
  },
  {
    "code": "1726",
    "name": "Table Mounted",
    "price": 14250,
    "finish": "Whi"
  },
  {
    "code": "1739",
    "name": "Table Mounted",
    "price": 8000,
    "finish": "White"
  },
  {
    "code": "1747",
    "name": "Table Mounted 1764 W Table Mounted",
    "price": 21500,
    "finish": "White"
  },
  {
    "code": "1713",
    "name": "Table Mounted",
    "price": 5500,
    "finish": "White"
  },
  {
    "code": "1725",
    "name": "Table Mounted 1733 W Table Mounted",
    "price": 9000,
    "finish": "White"
  },
  {
    "code": "1746",
    "name": "Table Mounted",
    "price": 9500,
    "finish": "White"
  },
  {
    "code": "1763",
    "name": "Table Mounted",
    "price": 12000,
    "finish": "White"
  },
  {
    "code": "1604",
    "name": "Table Mounted",
    "price": 3900,
    "finish": "White"
  },
  {
    "code": "1719",
    "name": "Table Wall Mounted",
    "price": 7500,
    "finish": "White"
  },
  {
    "code": "1728",
    "name": "Table Mounted",
    "price": 15000,
    "finish": "White"
  },
  {
    "code": "1745",
    "name": "Table Mounted",
    "price": 8500,
    "finish": "White"
  },
  {
    "code": "1762",
    "name": "Table Mounted CERAMIC WASH BASINS 83 1782 W - Glossy White Table Mounted",
    "price": 14750,
    "finish": "White"
  },
  {
    "code": "1901",
    "name": "Table Wall Mounted",
    "price": 12500,
    "finish": "White"
  },
  {
    "code": "1908",
    "name": "Table Wall Mounted 1921 W Table Mounted",
    "price": 10500,
    "finish": "White"
  },
  {
    "code": "1926",
    "name": "Table Mounted",
    "price": 9950,
    "finish": "White"
  },
  {
    "code": "1773",
    "name": "Table Mounted",
    "price": 6500,
    "finish": "White"
  },
  {
    "code": "1900",
    "name": "Table Mounted",
    "price": 17500,
    "finish": "White Pearl White"
  },
  {
    "code": "1905",
    "name": "Table Wall Mounted Corner Wash Basin",
    "price": 5950,
    "finish": "White"
  },
  {
    "code": "1912",
    "name": "Table Mounted",
    "price": 16500,
    "finish": "White"
  },
  {
    "code": "1925",
    "name": "Table Mounted",
    "price": 12000,
    "finish": "White"
  },
  {
    "code": "1765",
    "name": "Table Mounted",
    "price": 21500,
    "finish": "White"
  },
  {
    "code": "1904",
    "name": "Table Mounted",
    "price": 5950,
    "finish": "White"
  },
  {
    "code": "1911",
    "name": "Table Mounted",
    "price": 6000,
    "finish": "White"
  },
  {
    "code": "1924",
    "name": "Table Mounted",
    "price": 12000,
    "finish": "White"
  },
  {
    "code": "1791",
    "name": "Table Wall Mounted MRP - White 7 550 1902 W - Glossy White Table Mounted",
    "price": 9950,
    "finish": "White"
  },
  {
    "code": "1909",
    "name": "Table Wall Mounted 1922 W Table Mounted",
    "price": 7250,
    "finish": "White"
  },
  {
    "code": "1927",
    "name": "Table Mounted CERAMIC WASH BASINS 84 1936 W Table Mounted MRP",
    "price": 6250,
    "finish": "White"
  },
  {
    "code": "1940",
    "name": "Table Mounted",
    "price": 6000,
    "finish": "White"
  },
  {
    "code": "1955",
    "name": "Table Mounted",
    "price": 11000,
    "finish": "White"
  },
  {
    "code": "1931",
    "name": "Table Mounted",
    "price": 7500,
    "finish": "White"
  },
  {
    "code": "1939",
    "name": "Table Mounted",
    "price": 8250,
    "finish": "White"
  },
  {
    "code": "1953",
    "name": "Table Mounted",
    "price": 9500,
    "finish": "White"
  },
  {
    "code": "1957",
    "name": "Table Mounted",
    "price": 12250,
    "finish": "White"
  },
  {
    "code": "1930",
    "name": "Table Mounted",
    "price": 28500,
    "finish": "White"
  },
  {
    "code": "1938",
    "name": "Table Mounted",
    "price": 7250,
    "finish": "White"
  },
  {
    "code": "1952",
    "name": "Table Mounted",
    "price": 8950,
    "finish": "White"
  },
  {
    "code": "1958",
    "name": "Table Mounted",
    "price": 8500,
    "finish": "White"
  },
  {
    "code": "1929",
    "name": "Table Wall Mounted",
    "price": 7450,
    "finish": "White"
  },
  {
    "code": "1937",
    "name": "Table Wall Mounted",
    "price": 5750,
    "finish": "White"
  },
  {
    "code": "1951",
    "name": "Table Mounted",
    "price": 8750,
    "finish": "White"
  },
  {
    "code": "1956",
    "name": "Table Mounted",
    "price": 11000,
    "finish": "White"
  },
  {
    "code": "1607",
    "name": "Semi Recessed CERAMIC WASH BASINS 85",
    "price": 14250,
    "finish": "White"
  },
  {
    "code": "1943",
    "name": "Three Hole Semi Counter Basin",
    "price": 13500,
    "finish": "White"
  },
  {
    "code": "1637",
    "name": "Under Counter",
    "price": 5300,
    "finish": "White"
  },
  {
    "code": "1947",
    "name": "Under Counter 1915 W Semi Counter Table Mounted",
    "price": 10500,
    "finish": "White"
  },
  {
    "code": "1941",
    "name": "Three Hole Semi Counter Basin 1923 W Under Counter",
    "price": 5850,
    "finish": "White"
  },
  {
    "code": "1946",
    "name": "Under Counter 1914 W Semi Counter Table Mounted",
    "price": 12900,
    "finish": "White"
  },
  {
    "code": "1720",
    "name": "Semi Counter",
    "price": 8000,
    "finish": "White"
  },
  {
    "code": "1715",
    "name": "Under Counter",
    "price": 4500,
    "finish": "White"
  },
  {
    "code": "1954",
    "name": "Under Counter",
    "price": 11500,
    "finish": "White"
  },
  {
    "code": "1942",
    "name": "Semi Counter Basin",
    "price": 13500,
    "finish": "White"
  },
  {
    "code": "1961",
    "name": "Semi Counter Basin",
    "price": 16500,
    "finish": "White"
  },
  {
    "code": "1945",
    "name": "Under Counter",
    "price": 12500,
    "finish": "White"
  },
  {
    "code": "1944",
    "name": "Semi Counter Basin",
    "price": 12500,
    "finish": "White"
  },
  {
    "code": "1962",
    "name": "Three Hole Semi Counter Basin INTELLIGENT SMART TOILETS SERIES AoUAN XX E 86 Extra - Intelligent Toilet Seat Extra - Intelligent Toilet Remote 1506 - Concealed Pneumatic Cistern Intelligent Smart Toilet Extra - Intelligent Toilet Seat Extra - Intelligent Toilet Remote Extra - Doorbell Remote Floor Mounted Smart Toilet SmartLuxe Intelligent Toilet 1860 - SmartLuxe In-Built Flush Tank E-Functions Capacity Auto Opening & Closing Foot Sensing For Toilet Seat & Flip Seat Auto Flushing Self Cleaning Spray Before & After Use Running Water Instant Heating Water Source Filtration & UV Water Sterilization Pressure Regularization Ambient Light & Night Light Built-In UV Sterilization Lamp Seat Ring Heating Anti Bacterial & Flame Retardant No Water Pressure Limit While Flushing Silent Flushing Built-In Booster Pump Manual Multi Side Knob IPX4 Waterproof Design Wireless Remote Control A Masterpeice of Innovation where cutting-edge technology & elegent design unite setting the pinnacle of excellence Wall Hung Smart Toilet 1850 W - SmartElite Intelligent Rimless Wall Hung Toilet E-Functions Auto Opening & Closing Self Cleaning Spray Before & After Use Warm Air Drying Seat Ring Heating Adjustable Temperature For Water Air & Seat Night Lighting LED Anti Bacterial Wireless Remote Control SmartElite Intelligent Toilet A masterfully engineered intelligent WC combining smart expect comfort precision and sophistication INTELLIGENT SMART TOILETS SERIES AoUAN XX E Extra - Intelligent Toilet Remote Extra - Intelligent Toilet Seat 87 Extra - Intelligent Toilet Seat Extra - Int",
    "price": 1,
    "finish": "White"
  },
  {
    "code": "1864",
    "name": "Generation 3 Rimless Tornado Silent Close UF Seat Cover 1865 W Generation 3 - Rimless Tornado Silent Close UF Slim Seat Cover 1857 W Generation 3 Rimless Tornado Silent Swirl Tornado-Swirl Flushing Wall Hung Toilets",
    "price": 27500,
    "finish": "White"
  },
  {
    "code": "1853",
    "name": "Generation 3 Rimless Tornado Silent Swirl",
    "price": 26500,
    "finish": "White"
  },
  {
    "code": "1863",
    "name": "Generation 3 Rimless Tornado Silent Swirl UF Slim Seat Cover",
    "price": 29500,
    "finish": "White"
  },
  {
    "code": "1852",
    "name": "Generation 3 Rimless Tornado Silent Swirl",
    "price": 26500,
    "finish": "White"
  },
  {
    "code": "1862",
    "name": "Generation 3 Relax Model - Rimless Tornado Silent Swirl Flushing Wall Hung Ergonomically Designed Seat",
    "price": 27500,
    "finish": "White"
  },
  {
    "code": "1830",
    "name": "Seat Cover",
    "price": 25500,
    "finish": "White"
  },
  {
    "code": "1866",
    "name": "Generation 3 Rimless Tornado Silent Swirl UF Slim Seat Cover 88 Tornado Generation 3 TOILETS 1848 W",
    "price": 17950,
    "finish": "White"
  },
  {
    "code": "1810",
    "name": "1832 Mini",
    "price": 17950,
    "finish": "White"
  },
  {
    "code": "1820",
    "name": "1831 J 1837 W",
    "price": 13500,
    "finish": "White"
  },
  {
    "code": "1819",
    "name": "1833 J 89 1851 W 1816 W 1830 B Seat Cover 1831 W Rimless Wall Hung Toilets TOILETS Floor Mounted Couple Suites",
    "price": 17950,
    "finish": "White"
  },
  {
    "code": "1641",
    "name": "Back Inlet Back Outlet All PVC Seat Covers 2 Piece Floor Mounted Couple Suite Trap\u0003Distance\u0003 1643 W Back Inlet Back-Floor Outlet All UF Seat Covers 1 Piece Floor Mounted Couple Suite Trap\u0003Distance\u0003",
    "price": 5500,
    "finish": "White"
  },
  {
    "code": "1640",
    "name": "Top Inlet Floor Outlet Urinals Seat Covers Bidet Seat Cover Wall Hung Toilet",
    "price": 11000,
    "finish": "White"
  },
  {
    "code": "1570",
    "name": "Concealed Flush Tanks FLUSH TANKS FLUSH PLATES & URINAL SENSORS IN SPECIAL & CHROME FINISH ABS Flush Plate 1505 CP Brushed Stainless Steel Flush Plate (316 SS) 1507 BSS Urinal Sensor Auto & Manual Valve 1342 CP 91 Flush Plates Stainless Steel Flush Plate (304 SS) 1505 GG - Graphite Grey 1505 RG - Rose Gold 1505 BG - Brushed Gold 1505 MB - Matt Black 1505 G - Gold 1505 BRG - Brushed Rose Gold Stainless Steel Flush Plate (304 SS) 1507 GG - Graphite Grey 1507 BG - Brushed Gold 1507 MB - Matt Black 1507 BRG - Brushed Rose Gold Urinal Sensors Urinal Sensor Auto & Manual Valve 1342 GG - Graphite Grey 1342 RG - Rose Gold 1342 BG - Brushed Gold 1342 MB - Matt Black 1342 BRG - Brushed Rose Gold 1505 SSF Brushed Stainless Steel Brushed Stainless Steel Flush Plate (304 SS)",
    "price": 15250,
    "finish": "White"
  },
  {
    "code": "1501",
    "name": "Product",
    "price": 20990
  },
  {
    "code": "1502",
    "name": "Product",
    "price": 13990
  },
  {
    "code": "1503",
    "name": "Concealed Pneumatic Cistern OUR PROMISE Our promise to you We at Aquant are confident that your shower systems and sanitary ware will give you many years of trouble free operation however for peace of mind all our products are covered by the following service warranty 92 Residential Commercial Diverters 10 years 5 years Brass Faucets 10 years 5 years Concealed Multi-Function Showers 10 years 5 years Brass Showers 10 years 5 years Shower Panels 10 years 5 years Kitchen Faucets 10 years 5 years Kitchen Faucet s Rubber Tube & Flexible Tube 3 years 2 years Kitchen Faucet s Pullout Tube 3 years 2 years PVD Finishes (Bath",
    "price": 9990
  }
]